necika/__init__.py
necika/color.py
necika/constants.py
necika/exceptions.py
necika/palette.py
necika/terminal.py
necika/utils.py
necika-1.0.0.dist-info/METADATA
necika-1.0.0.dist-info/WHEEL
necika-1.0.0.dist-info/top_level.txt
necika-1.0.0.dist-info/RECORD
