Metadata-Version: 2.4
Name: necika
Version: 1.0.0
Summary: A comprehensive color manipulation library for Python
Author-email: CELESTIFYX Team <celestifyx@gmail.com>
License-Expression: GPL-3.0-or-later
Project-URL: Homepage, https://gitlab.com/celestifyx/necika
Project-URL: Repository, https://gitlab.com/celestifyx/necika
Project-URL: Issues, https://gitlab.com/celestifyx/necika/-/issues
Keywords: color,rgb,hsl,hsv,hex,ansi,terminal
Classifier: Programming Language :: Python :: 3.12
Classifier: Programming Language :: Python :: 3.13
Classifier: Topic :: Software Development :: Libraries :: Python Modules
Classifier: Topic :: Multimedia :: Graphics
Classifier: Operating System :: OS Independent
Requires-Python: >=3.12
